shiertier_scrapy/__init__.py
shiertier_scrapy/scrapy.py
shiertier_scrapy-0.0.5.dist-info/LICENSE
shiertier_scrapy-0.0.5.dist-info/METADATA
shiertier_scrapy-0.0.5.dist-info/WHEEL
shiertier_scrapy-0.0.5.dist-info/top_level.txt
shiertier_scrapy-0.0.5.dist-info/RECORD
